{"/LXNxHyefuUajKQCIrN2Iw==":"mbr-1920x1440.png","krQhURdpyHRwvSiCTAYepw==":"mbr-1256x838.jpg","bPea1FME58YDxZkUmaJRcw==":"mbr-596x397.jpg","wyZaTgR8X9VGejiCPXwvXw==":"mbr-1-596x397.jpg","Vc1xUkFyLcAR9N+01/9SPw==":"mbr-596x398.jpg","uFw90vyzVZ5gYQmyUIRbrQ==":"mbr-2-596x397.jpg","BbnwYTQ/mwRikIuzWrx5wQ==":"mbr-3-596x397.jpg","yj65sRuI116jFLEwblFzpQ==":"mbr-4-596x397.jpg","5oPK1SFHulevFYkrYKzJZA==":"mbr-596x447.jpg","avvqA70996b1K9wVBqlPyw==":"mbr-596x401.jpg","KonTLiEUyrslutBRFAYAsQ==":"mbr-596x401.jpeg","pOu5RVJOYUVtoRmCFCuY7Q==":"mbr-1920x1280.jpg","yhM3E1ZFr8dF18pJX8fqCw==":"mbr-1256x837.jpg","w83uDO7df7KKhPdDldUGYg==":"mbr-1-1920x1280.jpg","7+IaZveUPgj7KRGNlBTXbw==":"mbr-816x544.jpg","tCpP3Zby51T46L6MmgZSgA==":"mbr-1-816x544.jpg","lwgOQaWOCTYj+S01nb8m8g==":"mbr-816x524.jpg","8cRf2rMsVHRj++7zzvhg6w==":"mbr-198x198.jpg","hvxIYJbHmr3+Fqg1rCxUZQ==":"mbr-1256x829.jpg","WTiSxc+RzqBryHhl0Q0hjw==":"mbr-1256x1881.jpg","Q3P0+fJnfWAFJheTrMZqHw==":"mbr-1-1256x837.jpg","YL34aMyTf4LB6uaPWe5WVw==":"min-logo-81x69.png","xiVBfSmJVtlLa495N+hprw==":"_6c43a1aa-fde0-4eaa-861b-f1f3dfac0fdc-removebg-preview-501x500.png","0LdMPO+SR2dUEwbcCs02FA==":"_ce92eaef-d2ef-45a9-a759-4c78a146bdab-removebg-preview%20-158x157.png","FFI3S7JY09X6RqEjxx7i4w==":"_ca94c8ab-679f-4a8d-81a8-ef9ba866e69e-removebg-preview%201-158x157.png","1W2SMg+DVgVI9zLUw91j4g==":"_adff225d-da9d-408d-9586-ea1cb9a1ad7e-removebg-preview%201-158x157.png","4N0BTU4r6zaY/xmY9F++hg==":"_6fab5220-4655-456b-932f-bf6bb419952e-removebg-preview%201-146x145.png","M6pQCjIlQ2+U95tWhg1/Ng==":"_ceaf5a77-7fd7-419e-b510-efb8821a7191-removebg-preview%201-158x157.png"}